mtfl/__init__.py
mtfl/ast.py
mtfl/connective.py
mtfl/evaluator.py
mtfl/hypothesis.py
mtfl/parser.py
mtfl/sugar.py
mtfl/test_ast.py
mtfl/test_boolean_eval.py
mtfl/test_eval.py
mtfl/test_fuzzy.py
mtfl/test_fuzzy_connective.py
mtfl/test_params.py
mtfl/test_parser.py
mtfl/test_utils.py
mtfl/utils.py
metric_temporal_fuzzy_logic-0.0.6.dist-info/LICENSE
metric_temporal_fuzzy_logic-0.0.6.dist-info/WHEEL
metric_temporal_fuzzy_logic-0.0.6.dist-info/METADATA
metric_temporal_fuzzy_logic-0.0.6.dist-info/RECORD
