Metadata-Version: 2.1
Name: metric-temporal-fuzzy-logic
Version: 0.0.6
Summary: A library for manipulating and evaluating metric temporal (fuzzy) logic.
Home-page: https://github.com/Gaudeval/py-metric-temporal-fuzzy-logic
License: MIT
Author: Gaudeval
Requires-Python: >=3.7,<4.0
Classifier: License :: OSI Approved :: MIT License
Classifier: Programming Language :: Python :: 3
Classifier: Programming Language :: Python :: 3.10
Classifier: Programming Language :: Python :: 3.7
Classifier: Programming Language :: Python :: 3.8
Classifier: Programming Language :: Python :: 3.9
Requires-Dist: attrs (>=19.3.0,<20.0.0)
Requires-Dist: discrete-signals (>=0.7.3,<0.8.0)
Requires-Dist: lenses (>=0.5.0,<0.6.0)
Requires-Dist: parsimonious (>=0.8.1,<0.9.0)
Requires-Dist: pylint (>=2.6.0,<3.0.0)
Project-URL: Repository, https://github.com/Gaudeval/py-metric-temporal-fuzzy-logic
